toolrave/__init__.py
toolrave/main.py
toolrave/proxy.py
tool_rave_mcp-0.1.0.dist-info/METADATA
tool_rave_mcp-0.1.0.dist-info/WHEEL
tool_rave_mcp-0.1.0.dist-info/entry_points.txt
tool_rave_mcp-0.1.0.dist-info/RECORD
