Metadata-Version: 2.4
Name: tool-rave-mcp
Version: 0.1.0
Summary: Universal MCP server proxy that enables parallel tool execution for servers that don't support it natively
Author: Igor Tarasenko
License: MIT
Requires-Python: >=3.9
Requires-Dist: rich>=13.0.0
Requires-Dist: typer>=0.9.0
